norsecorpus/__init__.py
norsecorpus/__main__.py
norsecorpus/reader.py
norsecorpus/__pycache__/__init__.cpython-37.pyc
norsecorpus/__pycache__/reader.cpython-37.pyc
norsecorpus/data/heimskringla/Völsunga_saga/tei/volsunga.xml
norsecorpus/data/heimskringla/Völsunga_saga/txt/chapter_1.txt
norsecorpus/data/heimskringla/Völsunga_saga/txt/chapter_10.txt
norsecorpus/data/heimskringla/Völsunga_saga/txt/chapter_11.txt
norsecorpus/data/heimskringla/Völsunga_saga/txt/chapter_12.txt
norsecorpus/data/heimskringla/Völsunga_saga/txt/chapter_13.txt
norsecorpus/data/heimskringla/Völsunga_saga/txt/chapter_14.txt
norsecorpus/data/heimskringla/Völsunga_saga/txt/chapter_15.txt
norsecorpus/data/heimskringla/Völsunga_saga/txt/chapter_16.txt
norsecorpus/data/heimskringla/Völsunga_saga/txt/chapter_17.txt
norsecorpus/data/heimskringla/Völsunga_saga/txt/chapter_18.txt
norsecorpus/data/heimskringla/Völsunga_saga/txt/chapter_19.txt
norsecorpus/data/heimskringla/Völsunga_saga/txt/chapter_2.txt
norsecorpus/data/heimskringla/Völsunga_saga/txt/chapter_20.txt
norsecorpus/data/heimskringla/Völsunga_saga/txt/chapter_21.txt
norsecorpus/data/heimskringla/Völsunga_saga/txt/chapter_22.txt
norsecorpus/data/heimskringla/Völsunga_saga/txt/chapter_23.txt
norsecorpus/data/heimskringla/Völsunga_saga/txt/chapter_24.txt
norsecorpus/data/heimskringla/Völsunga_saga/txt/chapter_25.txt
norsecorpus/data/heimskringla/Völsunga_saga/txt/chapter_26.txt
norsecorpus/data/heimskringla/Völsunga_saga/txt/chapter_27.txt
norsecorpus/data/heimskringla/Völsunga_saga/txt/chapter_28.txt
norsecorpus/data/heimskringla/Völsunga_saga/txt/chapter_29.txt
norsecorpus/data/heimskringla/Völsunga_saga/txt/chapter_3.txt
norsecorpus/data/heimskringla/Völsunga_saga/txt/chapter_30.txt
norsecorpus/data/heimskringla/Völsunga_saga/txt/chapter_31.txt
norsecorpus/data/heimskringla/Völsunga_saga/txt/chapter_32.txt
norsecorpus/data/heimskringla/Völsunga_saga/txt/chapter_33.txt
norsecorpus/data/heimskringla/Völsunga_saga/txt/chapter_34.txt
norsecorpus-1.0.2.dist-info/LICENSE
norsecorpus-1.0.2.dist-info/METADATA
norsecorpus-1.0.2.dist-info/WHEEL
norsecorpus-1.0.2.dist-info/entry_points.txt
norsecorpus-1.0.2.dist-info/top_level.txt
norsecorpus-1.0.2.dist-info/zip-safe
norsecorpus-1.0.2.dist-info/RECORD
