Metadata-Version: 2.1
Name: norsecorpus
Version: 1.0.2
Summary: Corpus of Old Norse texts with code to read them
Home-page: https://github.com/clemsciences/old_norse_corpus
Author: Clément Besnier
Author-email: clemsciences@aol.com
License: License :: OSI Approved :: MIT License
Keywords: old-norse,corpus
Platform: UNKNOWN
Classifier: Programming Language :: Python :: 3
Classifier: Operating System :: OS Independent
Classifier: License :: OSI Approved :: MIT License
Classifier: Topic :: Text Processing
Classifier: Topic :: Text Processing :: Markup :: XML
Requires-Python: >=3.6
Requires-Dist: nltk
Requires-Dist: lxml
